LICENSE.txt
README.rst
setup.py
oboipark_utils/AsuncRequests.py
oboipark_utils/TextWorker.py
oboipark_utils/__init__.py
oboipark_utils.egg-info/PKG-INFO
oboipark_utils.egg-info/SOURCES.txt
oboipark_utils.egg-info/dependency_links.txt
oboipark_utils.egg-info/requires.txt
oboipark_utils.egg-info/top_level.txt