Metadata-Version: 2.1
Name: oboipark-utils
Version: 0.0.13
Summary: утилиты для обоипарк
Home-page: https://gitlab.com/oboipark/utils
Author: VVD-byte
Author-email: vovavoronin1999@gmail.com
License: python
Platform: UNKNOWN
License-File: LICENSE.txt
